{"1": {"py/object": "Domain.film.Film", "id_entity": "1", "titlu": "divergent", "an_aparitie": 2013, "pret_bilet": 20.5, "in_program": "da"}, "2": {"py/object": "Domain.film.Film", "id_entity": "2", "titlu": "insurgent", "an_aparitie": 2016, "pret_bilet": 21.0, "in_program": "da"}, "3": {"py/object": "Domain.film.Film", "id_entity": "3", "titlu": "titanic", "an_aparitie": 2002, "pret_bilet": 15.9, "in_program": "nu"}, "4": {"py/object": "Domain.film.Film", "id_entity": "4", "titlu": "parker", "an_aparitie": 2015, "pret_bilet": 18.0, "in_program": "da"}, "9": {"py/object": "Domain.film.Film", "id_entity": "9", "titlu": "Fast and furious 7", "an_aparitie": 2000, "pret_bilet": 23.3, "in_program": "da"}, "15": {"py/object": "Domain.film.Film", "id_entity": "15", "titlu": "The Great Gatsby", "an_aparitie": 2003, "pret_bilet": 24.5, "in_program": "da"}, "5": {"py/object": "Domain.film.Film", "id_entity": "5", "titlu": "nerve", "an_aparitie": 2017, "pret_bilet": 19.0, "in_program": "da"}, "11": {"py/object": "Domain.film.Film", "id_entity": "11", "titlu": "the maze", "an_aparitie": 2015, "pret_bilet": 17.5, "in_program": "nu"}, "12": {"py/object": "Domain.film.Film", "id_entity": "12", "titlu": "the nun", "an_aparitie": 2016, "pret_bilet": 18, "in_program": "da"}, "21": {"py/object": "Domain.film.Film", "id_entity": "21", "titlu": "the maze", "an_aparitie": 2015, "pret_bilet": 17.5, "in_program": "nu"}, "22": {"py/object": "Domain.film.Film", "id_entity": "22", "titlu": "the nun", "an_aparitie": 2016, "pret_bilet": 18, "in_program": "da"}, "30": {"py/object": "Domain.film.Film", "id_entity": "30", "titlu": "venom", "an_aparitie": 2020, "pret_bilet": 13.5, "in_program": "nu"}, "27": {"py/object": "Domain.film.Film", "id_entity": "27", "titlu": "venom2", "an_aparitie": 2021, "pret_bilet": 19.5, "in_program": "da"}, "32": {"py/object": "Domain.film.Film", "id_entity": "32", "titlu": "venom3", "an_aparitie": 2021, "pret_bilet": 20.0, "in_program": "da"}}